{
  "total": 869,
  "alive": 358,
  "top_countries": [
    [
      "CA",
      120
    ],
    [
      "DE",
      58
    ],
    [
      "US",
      38
    ],
    [
      "NL",
      31
    ],
    [
      "FI",
      22
    ],
    [
      "FR",
      20
    ],
    [
      "GB",
      9
    ],
    [
      "HK",
      8
    ],
    [
      "SG",
      8
    ],
    [
      "SC",
      5
    ]
  ],
  "top_protocols": [
    [
      "vmess",
      198
    ],
    [
      "vless",
      112
    ],
    [
      "ss",
      29
    ],
    [
      "trojan",
      19
    ]
  ],
  "avg_latency_ms": 108.4,
  "min_latency_ms": 8.3
}